fakr/CompoundMappingSequence.py
fakr/Generator.py
fakr/Jinja2Renderer.py
fakr/TemplatedMapping.py
fakr/__init__.py
fakr/__version__.py
fakr/cli.py
fakr/jinja.py
fakr/vocabulary.py
fakr/vocabulary_builder.py
fakr/vocabularies/us_business.fakr
fakr-0.1.1.dist-info/DESCRIPTION.rst
fakr-0.1.1.dist-info/METADATA
fakr-0.1.1.dist-info/RECORD
fakr-0.1.1.dist-info/WHEEL
fakr-0.1.1.dist-info/entry_points.txt
fakr-0.1.1.dist-info/metadata.json
fakr-0.1.1.dist-info/top_level.txt
