Metadata-Version: 2.0
Name: fakr
Version: 0.1.1
Summary: Random data generator for the command line
Home-page: http://github.com/l-x/fakr
Author: l-x
Author-email: l-x@mailbox.org
License: MIT
Download-URL: http://github.com/l-x/fakr/archive/0.1.1.tar.gz
Keywords: fake template random list data generator Jinja2 fakr
Platform: UNKNOWN
Classifier: Development Status :: 3 - Alpha
Classifier: License :: OSI Approved :: MIT License
Classifier: Programming Language :: Python :: 3.4
Classifier: Programming Language :: Python :: 3 :: Only
Classifier: Environment :: Console
Classifier: Intended Audience :: Developers
Classifier: Natural Language :: English
Classifier: Topic :: Software Development
Classifier: Topic :: Software Development :: Testing
Classifier: Topic :: Software Development :: Testing :: Traffic Generation
Requires-Dist: jinja2
Requires-Dist: unidecode
